abcoder/__init__.py
abcoder/atomic.py
abcoder/backend.py
abcoder/cli.py
abcoder/server.py
abcoder/util.py
abcoder-0.3.1.dist-info/METADATA
abcoder-0.3.1.dist-info/WHEEL
abcoder-0.3.1.dist-info/entry_points.txt
abcoder-0.3.1.dist-info/licenses/LICENSE
abcoder-0.3.1.dist-info/RECORD
