Metadata-Version: 2.4
Name: abcoder
Version: 0.3.1
Summary: Agentic bioinformatics coder
Project-URL: Homepage, https://github.com/huang-sh/abcoder
Project-URL: Repository, https://github.com/huang-sh/abcoder
Project-URL: Documentation, https://github.com/huang-sh/abcoder
Author-email: shuang <hsh-me@outlook.com>
License-File: LICENSE
Keywords: AI,agent,bioinformatics,llm,mcp,model context protocol,scRNA-seq,single cell
Requires-Python: >=3.10
Requires-Dist: fastmcp>=2.7.0
Requires-Dist: ipykernel
Requires-Dist: jupyter-client
Requires-Dist: mcp>=1.8.0
